caqtus_devices/pulse_generators/swabian_instruments_pulse_streamer/__init__.py
caqtus_devices/pulse_generators/swabian_instruments_pulse_streamer/_compiler.py
caqtus_devices/pulse_generators/swabian_instruments_pulse_streamer/_extension.py
caqtus_devices/pulse_generators/swabian_instruments_pulse_streamer/configuration/__init__.py
caqtus_devices/pulse_generators/swabian_instruments_pulse_streamer/configuration/py.typed
caqtus_devices/pulse_generators/swabian_instruments_pulse_streamer/configuration/swabian_pulse_streamer_configuration.py
caqtus_devices/pulse_generators/swabian_instruments_pulse_streamer/configuration_editor/__init__.py
caqtus_devices/pulse_generators/swabian_instruments_pulse_streamer/configuration_editor/py.typed
caqtus_devices/pulse_generators/swabian_instruments_pulse_streamer/configuration_editor/swabian_pulse_streamer_configuration_editor.py
caqtus_devices/pulse_generators/swabian_instruments_pulse_streamer/runtime/__init__.py
caqtus_devices/pulse_generators/swabian_instruments_pulse_streamer/runtime/py.typed
caqtus_devices/pulse_generators/swabian_instruments_pulse_streamer/runtime/swabian_pulse_streamer.py
caqtus_devices_swabian_instruments_pulse_streamer-1.16.0.dist-info/METADATA
caqtus_devices_swabian_instruments_pulse_streamer-1.16.0.dist-info/WHEEL
caqtus_devices_swabian_instruments_pulse_streamer-1.16.0.dist-info/licenses/license.md
caqtus_devices_swabian_instruments_pulse_streamer-1.16.0.dist-info/RECORD
