Metadata-Version: 2.4
Name: caqtus-devices-swabian-instruments-pulse-streamer
Version: 1.16.0
Summary: Contains the caqtus device extension for the Swabian instruments Pulse Streamer.
Author-email: light-scattering-io <lecaqtus66@gmail.com>
License: Copyright 2024 Université Paris-Saclay
License-File: license.md
Requires-Python: >=3.12
Requires-Dist: caqtus-suite>=6.18.1
Requires-Dist: pulsestreamer>=1.7.0
